{"schema_version":"v1","data":{"/home/fais/punk.systems/code/unity/fishr":{"title":"fishr","lastModified":1754165816534,"isCustomEditor":false,"path":"/home/fais/punk.systems/code/unity/fishr","containingFolderPath":"/home/fais/punk.systems/code/unity","version":"6000.1.14f1","architecture":"x86_64","changeset":"db7aa045cc2c","isFavorite":false,"genesisOrgId":"9071096487910","cloudProjectId":"a5745d79-42cf-4835-a023-5f4b6bb88c84","organizationId":"xial649","localProjectId":"70e843833ef5b6f82ad8bc9087b82dca","cloudEnabled":true,"projectName":"fishr","organizationName":"9071096487910","repositoryName":"fishr/fishr","projectPathInsideRepository":"","plasticConfigurationFilePath":"/home/fais/punk.systems/code/unity/fishr/.plastic/plastic.selector"}}}